{
  "adversarial-review": {
    "archived_at": null,
    "created_at": "2026-07-08T06:53:56.125419+00:00",
    "created_by": null,
    "last_patched_at": null,
    "last_used_at": null,
    "last_viewed_at": null,
    "patch_count": 0,
    "pinned": true,
    "state": "active",
    "use_count": 0,
    "view_count": 0
  },
  "dev-dispatch": {
    "archived_at": null,
    "created_at": "2026-07-07T17:04:29.723407+00:00",
    "created_by": null,
    "last_patched_at": "2026-07-08T06:51:12.575585+00:00",
    "last_used_at": "2026-07-09T21:06:38.582469+00:00",
    "last_viewed_at": "2026-07-09T21:06:38.580187+00:00",
    "patch_count": 14,
    "pinned": true,
    "state": "active",
    "use_count": 55,
    "view_count": 55
  },
  "dev-planning": {
    "archived_at": null,
    "created_at": "2026-07-07T17:04:23.082941+00:00",
    "created_by": null,
    "last_patched_at": "2026-07-08T06:50:52.191823+00:00",
    "last_used_at": "2026-07-08T19:42:56.916020+00:00",
    "last_viewed_at": "2026-07-08T19:42:56.908638+00:00",
    "patch_count": 17,
    "pinned": true,
    "state": "active",
    "use_count": 41,
    "view_count": 41
  },
  "grill-me": {
    "archived_at": null,
    "created_at": "2026-07-07T20:38:30.436800+00:00",
    "created_by": null,
    "last_patched_at": null,
    "last_used_at": "2026-07-07T20:38:30.436811+00:00",
    "last_viewed_at": null,
    "patch_count": 0,
    "pinned": false,
    "state": "active",
    "use_count": 1,
    "view_count": 0
  },
  "grilling": {
    "archived_at": null,
    "created_at": "2026-07-07T20:38:38.224619+00:00",
    "created_by": null,
    "last_patched_at": null,
    "last_used_at": "2026-07-07T20:38:38.226634+00:00",
    "last_viewed_at": "2026-07-07T20:38:38.224629+00:00",
    "patch_count": 0,
    "pinned": false,
    "state": "active",
    "use_count": 1,
    "view_count": 1
  },
  "hermes-agent-skill-authoring": {
    "archived_at": null,
    "created_at": "2026-07-05T18:33:46.476839+00:00",
    "created_by": null,
    "last_patched_at": "2026-07-08T19:44:09.884752+00:00",
    "last_used_at": "2026-07-08T19:43:21.983911+00:00",
    "last_viewed_at": "2026-07-08T19:43:21.977487+00:00",
    "patch_count": 10,
    "pinned": false,
    "state": "active",
    "use_count": 13,
    "view_count": 13
  },
  "hermes-cron-admin": {
    "archived_at": null,
    "created_at": "2026-07-08T19:10:11.874392+00:00",
    "created_by": "agent",
    "last_patched_at": "2026-07-08T19:10:30.484787+00:00",
    "last_used_at": null,
    "last_viewed_at": null,
    "patch_count": 1,
    "pinned": false,
    "state": "active",
    "use_count": 0,
    "view_count": 0
  },
  "intercom": {
    "archived_at": null,
    "created_at": "2026-07-08T12:47:50.778357+00:00",
    "created_by": "agent",
    "last_patched_at": "2026-07-08T19:45:18.815200+00:00",
    "last_used_at": "2026-07-08T19:45:11.677056+00:00",
    "last_viewed_at": "2026-07-08T19:45:11.670947+00:00",
    "patch_count": 31,
    "pinned": false,
    "state": "active",
    "use_count": 23,
    "view_count": 23
  },
  "loops-engineering": {
    "archived_at": null,
    "created_at": "2026-07-08T06:53:55.908815+00:00",
    "created_by": null,
    "last_patched_at": null,
    "last_used_at": null,
    "last_viewed_at": null,
    "patch_count": 0,
    "pinned": true,
    "state": "active",
    "use_count": 0,
    "view_count": 0
  },
  "project-discovery": {
    "archived_at": null,
    "created_at": "2026-07-02T04:30:44.247466+00:00",
    "created_by": null,
    "last_patched_at": "2026-07-05T18:00:25.947900+00:00",
    "last_used_at": "2026-07-08T19:04:54.204143+00:00",
    "last_viewed_at": "2026-07-08T19:04:54.197352+00:00",
    "patch_count": 13,
    "pinned": false,
    "state": "active",
    "use_count": 26,
    "view_count": 24
  },
  "research": {
    "archived_at": null,
    "created_at": "2026-07-05T04:00:30.367964+00:00",
    "created_by": null,
    "last_patched_at": null,
    "last_used_at": "2026-07-05T04:06:11.894205+00:00",
    "last_viewed_at": "2026-07-05T04:06:11.892123+00:00",
    "patch_count": 0,
    "pinned": false,
    "state": "active",
    "use_count": 3,
    "view_count": 3
  },
  "scrutinize": {
    "archived_at": null,
    "created_at": "2026-07-06T05:36:32.080928+00:00",
    "created_by": null,
    "last_patched_at": null,
    "last_used_at": "2026-07-06T05:36:32.083494+00:00",
    "last_viewed_at": "2026-07-06T05:36:32.080945+00:00",
    "patch_count": 0,
    "pinned": false,
    "state": "active",
    "use_count": 1,
    "view_count": 1
  },
  "task-hygiene-validator": {
    "archived_at": null,
    "created_at": "2026-07-02T04:36:40.419135+00:00",
    "created_by": null,
    "last_patched_at": "2026-07-02T10:25:19.860435+00:00",
    "last_used_at": "2026-07-07T14:30:35.606784+00:00",
    "last_viewed_at": "2026-07-02T10:23:15.149583+00:00",
    "patch_count": 22,
    "pinned": false,
    "state": "active",
    "use_count": 57,
    "view_count": 31
  },
  "team-delegation": {
    "archived_at": null,
    "created_at": "2026-07-04T14:20:51.898838+00:00",
    "created_by": null,
    "last_patched_at": "2026-07-08T12:25:02.069488+00:00",
    "last_used_at": "2026-07-08T12:24:13.952031+00:00",
    "last_viewed_at": "2026-07-08T12:24:13.949365+00:00",
    "patch_count": 66,
    "pinned": false,
    "state": "active",
    "use_count": 43,
    "view_count": 43
  },
  "to-spec": {
    "archived_at": null,
    "created_at": "2026-07-04T23:22:50.104701+00:00",
    "created_by": null,
    "last_patched_at": null,
    "last_used_at": "2026-07-08T08:05:20.265069+00:00",
    "last_viewed_at": "2026-07-04T23:22:50.104719+00:00",
    "patch_count": 0,
    "pinned": false,
    "state": "active",
    "use_count": 5,
    "view_count": 1
  },
  "to-tickets": {
    "archived_at": null,
    "created_at": "2026-07-04T23:23:23.050967+00:00",
    "created_by": null,
    "last_patched_at": null,
    "last_used_at": "2026-07-08T19:04:46.824108+00:00",
    "last_viewed_at": "2026-07-08T19:04:46.818333+00:00",
    "patch_count": 0,
    "pinned": false,
    "state": "active",
    "use_count": 9,
    "view_count": 4
  },
  "transform": {
    "archived_at": null,
    "created_at": "2026-07-08T19:37:41.722874+00:00",
    "created_by": null,
    "last_patched_at": null,
    "last_used_at": "2026-07-08T19:37:41.725328+00:00",
    "last_viewed_at": "2026-07-08T19:37:41.722890+00:00",
    "patch_count": 0,
    "pinned": false,
    "state": "active",
    "use_count": 1,
    "view_count": 1
  },
  "web-research": {
    "archived_at": null,
    "created_at": "2026-07-05T04:01:04.663615+00:00",
    "created_by": "agent",
    "last_patched_at": "2026-07-05T04:09:39.431221+00:00",
    "last_used_at": "2026-07-07T17:11:16.464323+00:00",
    "last_viewed_at": "2026-07-07T17:11:16.461829+00:00",
    "patch_count": 8,
    "pinned": false,
    "state": "active",
    "use_count": 10,
    "view_count": 10
  },
  "writing-great-skills": {
    "archived_at": null,
    "created_at": "2026-07-05T05:08:46.601771+00:00",
    "created_by": null,
    "last_patched_at": null,
    "last_used_at": "2026-07-08T08:08:27.871934+00:00",
    "last_viewed_at": "2026-07-08T08:08:27.865844+00:00",
    "patch_count": 0,
    "pinned": false,
    "state": "active",
    "use_count": 7,
    "view_count": 5
  }
}